datastretch/__init__.py
datastretch/core/Task.py
datastretch/core/__init__.py
datastretch/exceptions/AccessException.py
datastretch/exceptions/AssignmentError.py
datastretch/exceptions/CompilationError.py
datastretch/exceptions/PipelineRuntimeError.py
datastretch/exceptions/__init__.py
datastretch/pipeline/Pipeline.py
datastretch/pipeline/Scheduler.py
datastretch/pipeline/Stage.py
datastretch/pipeline/__init__.py
datastretch/visualizing/Plotter.py
datastretch/visualizing/__init__.py
datastretch-0.0.5.dist-info/LICENSE
datastretch-0.0.5.dist-info/METADATA
datastretch-0.0.5.dist-info/WHEEL
datastretch-0.0.5.dist-info/top_level.txt
datastretch-0.0.5.dist-info/RECORD
