Metadata-Version: 2.1
Name: datastretch
Version: 0.0.5
Summary: DaTaStretch provides an easy and simple pipeline-framework
Home-page: https://github.com/RouladenRobert/Pypeline
Author: Jonas Seng
Author-email: jonas.seng1@gmail.com
License: MIT
Platform: UNKNOWN
Classifier: Programming Language :: Python :: 3
Classifier: License :: OSI Approved :: MIT License
Classifier: Operating System :: OS Independent
Classifier: Topic :: Scientific/Engineering
Classifier: Topic :: Software Development
Requires-Python: >=3
Requires-Dist: matplotlib
Requires-Dist: networkx
